[
    {
		"tipo": "Moradia",
		"tipologia": "V3",
		"estado": "Novo",
		"pais": "Portugal",
		"distrito": "Vila Real",
		"concelho": "Vila Real",
		"freguesia": "Vila Marim",
		"descricao": "Moradia para restaurar a 5 min do centro de Vila Real. Zona com excelentes acessos.",
		"ano": 2022,
		"preco": 450000,
		"imagens": [
			"/imagens/imovel1/1.jpg",
			"/imagens/imovel1/2.jpg",
			"/imagens/imovel1/3.jpg"
		]
	},
    {
		"tipo": "Apartamento",
		"tipologia": "T2",
		"estado": "Usado",
		"pais": "Portugal",
		"distrito": "Porto",
		"concelho": "Matosinhos",
		"freguesia": "",
		"descricao": "Apartamento T2 usado na zona de matosinhos, ótimo para rentabilizar.",
		"ano": 2010,
		"preco": 200000,
		"imagens": [
			"/imagens/imovel2/1.jpg",
			"/imagens/imovel2/2.jpg"
		]
	},
	{
		"tipo": "Apartamento",
		"tipologia": "T0",
		"estado": "novo",
		"pais": "Portugal",
		"distrito": "Vila Real",
		"concelho": "Vila Real",
		"freguesia": "Vila Real",
		"descricao": "Moradia para restaurar a 5 min do centro de Vila Real. Zona com excelentes acessos.",
		"ano": 2022,
		"preco": 150000,
		"imagens": [
			"/imagens/imovel3/1.jpg",
			"/imagens/imovel3/2.jpg",
			"/imagens/imovel3/3.jpg"
		]
	}
]